erogamescape/__init__.py
erogamescape/erogamescape.py
erogamescape/exception.py
erogamescape-0.0.3.dist-info/DESCRIPTION.rst
erogamescape-0.0.3.dist-info/METADATA
erogamescape-0.0.3.dist-info/RECORD
erogamescape-0.0.3.dist-info/WHEEL
erogamescape-0.0.3.dist-info/metadata.json
erogamescape-0.0.3.dist-info/top_level.txt
