Metadata-Version: 2.0
Name: erogamescape
Version: 0.0.3
Summary: erogamescape api for python
Home-page: http://github.com/roronya/erogamescape
Author: roronya
Author-email: roronya628@gmail.com
License: MIT
Keywords: erogamescape api
Platform: UNKNOWN
Classifier: Development Status :: 5 - Production/Stable
Classifier: Intended Audience :: Developers
Classifier: Topic :: Software Development :: Libraries
Classifier: License :: OSI Approved :: MIT License
Classifier: Programming Language :: Python :: 3
Requires-Dist: beautifulsoup4
Requires-Dist: lxml
Requires-Dist: requests
